sleepyconvert.py
sleepyconvert_toolchain/commands.py
sleepyconvert_toolchain/params.py
sleepyconvert_toolchain/utils.py
sleepyconvert-1.0.5.dist-info/LICENSE
sleepyconvert-1.0.5.dist-info/METADATA
sleepyconvert-1.0.5.dist-info/WHEEL
sleepyconvert-1.0.5.dist-info/RECORD
