Metadata-Version: 2.3
Name: sleepyconvert
Version: 1.0.5
Summary: Converts data files, images and documents to different formats
License: GNU GENERAL PUBLIC LICENSE
Keywords: pandas,data,documents,images,converter,cli
Author: Isaac Yep
Author-email: anthonybenchyep@gmail.com
Requires-Python: >=3.10
Classifier: License :: Other/Proprietary License
Classifier: Programming Language :: Python :: 3
Classifier: Programming Language :: Python :: 3.10
Classifier: Programming Language :: Python :: 3.11
Classifier: Programming Language :: Python :: 3.12
Classifier: Programming Language :: Python :: 3.13
Requires-Dist: Markdown (>=3.7,<4.0.0)
Requires-Dist: PyMuPDF (>=1.25.5,<2.0.0)
Requires-Dist: html2text (>=2024.2.26,<2025.0.0)
Requires-Dist: openpyxl (>=3.1.5,<4.0.0)
Requires-Dist: pandas (>=1.5.1,<2.0.0)
Requires-Dist: pyarrow (>=11.0,<12.0)
Requires-Dist: typer (>=0.15,<1.0.0)
Requires-Dist: weasyprint (>=65.0,<66.0)
Project-URL: Repository, https://github.com/anthonybench/convert
